markovchain/__init__.py
markovchain/__main__.py
markovchain/base.py
markovchain/info.py
markovchain/parser.py
markovchain/scanner.py
markovchain/util.py
markovchain/cli/__init__.py
markovchain/cli/__main__.py
markovchain/cli/image.py
markovchain/cli/main.py
markovchain/cli/text.py
markovchain/cli/util.py
markovchain/image/__init__.py
markovchain/image/markov.py
markovchain/image/scanner.py
markovchain/image/traversal.py
markovchain/image/type.py
markovchain/image/util.py
markovchain/storage/__init__.py
markovchain/storage/base.py
markovchain/storage/json.py
markovchain/storage/sqlite.py
markovchain/text/__init__.py
markovchain/text/formatter.py
markovchain/text/markov.py
markovchain/text/rank.py
markovchain/text/scanner.py
markovchain/text/util.py
markovchain-0.2.6.dist-info/LICENSE
markovchain-0.2.6.dist-info/METADATA
markovchain-0.2.6.dist-info/WHEEL
markovchain-0.2.6.dist-info/entry_points.txt
markovchain-0.2.6.dist-info/top_level.txt
markovchain-0.2.6.dist-info/RECORD
